{
  "name": "Lê Ngọa Triều",
  "birth": [
    "15 tháng 11, 986"
  ],
  "death": [
    "19 tháng 11, 1009 (23 tuổi)",
    "Đại Cồ Việt"
  ],
  "infoList": [
    {
      "label": "Trị vì",
      "info": [
        "1005 – 1009"
      ]
    },
    {
      "label": "Tiền nhiệm",
      "info": [
        "Lê Trung Tông"
      ]
    },
    {
      "label": "Kế nhiệm",
      "info": [
        "Triều đại sụp đổ"
      ]
    },
    {
      "label": "Hậu duệ",
      "info": [
        "Hậu duệ Khai Phong Vương Lê Long Sạ Khai Phong Vương Lê Long Sạ"
      ]
    },
    {
      "label": "Tên thật",
      "info": [
        "Lê Long Đĩnh (黎龍鋌)",
        "Lê Chí Trung (黎至忠)"
      ]
    },
    {
      "label": "Niên hiệu",
      "info": [
        "Ứng Thiên (應天)",
        "Cảnh Thụy (景瑞)"
      ]
    },
    {
      "label": "Thụy hiệu",
      "info": [
        "Ngọa Triều Hoàng Đế (臥朝皇帝) (do Lý Thái Tổ truy)",
        "Khai Thiên Ứng Vận Thánh Văn Thần Vũ Tắc Thiên Sùng Đạo Đại Thắng Minh Quang Hiếu Hoàng Đế (開天應運聖文神武則天崇道大勝明光孝皇帝) (tôn hiệu tự xưng của Lê đế Long Đĩnh và được mặc định thành thụy hiệu theo lễ pháp)"
      ]
    },
    {
      "label": "Triều đại",
      "info": [
        "Nhà Tiền Lê"
      ]
    },
    {
      "label": "Thân phụ",
      "info": [
        "Lê Đại Hành"
      ]
    },
    {
      "label": "Thân mẫu",
      "info": [
        "Chi hậu Diệu Nữ"
      ]
    }
  ],
  "description": "Lê Long Đĩnh (chữ Hán: 黎龍鋌; 15 tháng 11, 986 – 19 tháng 11, 1009), còn gọi là Lê Ngọa Triều (黎臥朝), là vị hoàng đế cuối cùng của nhà Tiền Lê trong lịch sử Việt Nam. Ông trị vì 4 năm từ năm 1005 đến năm 1009. Cái chết bí ẩn của ông ở tuổi 24 dẫn đến việc chấm dứt nhà Tiền Lê, quyền lực rơi vào tay nhà Lý.1"
}