{
  "name": "Lê Tư Tề",
  "birth": [
    "?"
  ],
  "death": [
    "1438",
    "Đại Việt"
  ],
  "infoList": [
    {
      "label": "Giám quốc",
      "info": [
        "1428 - 1433"
      ]
    },
    {
      "label": "Tên thật",
      "info": [
        "Lê Tư Tề (黎思齊)"
      ]
    },
    {
      "label": "Thụy hiệu",
      "info": [
        "Quận Ai vương (郡哀王)"
      ]
    },
    {
      "label": "Triều đại",
      "info": [
        "Nhà Hậu Lê"
      ]
    },
    {
      "label": "Thân phụ",
      "info": [
        "Lê Thái Tổ"
      ]
    },
    {
      "label": "Thân mẫu",
      "info": [
        "Trịnh Thị Ngọc Lữ"
      ]
    }
  ],
  "description": [
    "(chữ Hán: 黎思齊; ? – 1438), hay (郡哀王), là hoàng tử sơ trong lịch sử Việt Nam. Ông đã cùng cha là tham gia khởi nghĩa Lam Sơn đánh đuổi quân Minh, làm đến chức Tư đồ, thành lập Triều đại Sơ.",
    "Khi vua về già, ông được phong làm Quận vương, trông coi việc nước nhưng theo sách Đại Việt thông sử, do mắc chứng điên cuồng, hay giết bừa các tì thiếp. Vua vời người cháu ruột là Thái úy vào triều, bàn nên lập người con thứ làm vua, vua Thái Tổ nghe theo. Sau đó vua đã giam lỏng ông và phế làm thường dân, không rõ năm sinh, năm mất của Lê Tư Tề."
  ]
}