{
  "name": "Lý Càn Đức",
  "birth": [
    "22 tháng 2, 1066",
    "Du Thiền các, Thăng Long"
  ],
  "death": [
    "15 tháng 1, 1128 (61 tuổi)",
    "Điện Vĩnh Quang, Thăng Long"
  ],
  "infoList": [
    {
      "label": "Trị vì",
      "info": [
        "1072 – 1128"
      ]
    },
    {
      "label": "Tiền nhiệm",
      "info": [
        "Lý Thánh Tông"
      ]
    },
    {
      "label": "Nhiếp chính",
      "info": [
        "Thượng Dương thái hậu",
        "Lý Đạo Thành",
        "Linh Nhân thái hậu",
        "Lý Thường Kiệt"
      ]
    },
    {
      "label": "Kế nhiệm",
      "info": [
        "Lý Thần Tông"
      ]
    },
    {
      "label": "Tên húy",
      "info": [
        "Lý Càn Đức (李乾德)"
      ]
    },
    {
      "label": "Niên hiệu",
      "info": [
        "Thái Ninh (1072-1076)",
        "Anh Vũ Chiêu Thắng (1076-1084)",
        "Quảng Hựu (1085-1092)",
        "Hội Phong (1092-1100)",
        "Long Phù (1101-1109)",
        "Hội Tường Đại Khánh (1110-1119)",
        "Thiên Phù Duệ Vũ (1120-1126)",
        "Thiên Phù Khánh Thọ (1127-1127)"
      ]
    },
    {
      "label": "Thụy hiệu",
      "info": [
        "Hiếu Thiên Thể Đạo Thánh Văn Thần Vũ Sùng Nhân Ý Nghĩa Hiếu Từ Thuần Thành Minh Hiếu Hoàng Đế"
      ]
    },
    {
      "label": "Miếu hiệu",
      "info": [
        "Nhân Tông (仁宗)"
      ]
    },
    {
      "label": "Triều đại",
      "info": [
        "Nhà Lý"
      ]
    },
    {
      "label": "Thân phụ",
      "info": [
        "Lý Thánh Tông"
      ]
    },
    {
      "label": "Thân mẫu",
      "info": [
        "Linh Nhân hoàng hậu"
      ]
    },
    {
      "label": "An táng",
      "info": [
        "Lăng Thiên Đức"
      ]
    },
    {
      "label": "Tôn giáo",
      "info": [
        "Phật giáo"
      ]
    }
  ],
  "description": [
    "(chữ Hán: 李仁宗; 22 tháng 2 năm 1066 – 15 tháng 1 năm 1128) là vị hoàng đế thứ tư của nước Đại Việt. Ông trị vì từ năm 1072 đến năm 1128, tổng cộng 55 năm. Ông được xem là vị vua có thời gian ở ngôi lâu nhất trong lịch sử Việt Nam.",
    "Là con trai trưởng của , lên kế ngôi khi mới 7 tuổi. Với sự phụ chính của thái hậu Ỷ Lan, thái sư và thái úy , nhà vua đã củng cố được sự vững mạnh của Đại Việt. Ông khuyến khích nền giáo dục-khoa cử Nho học thông qua các biện pháp như mở khoa thi đầu tiên trong lịch sử khoa bảng Việt Nam (1072) và xây dựng trường Quốc tử giám (1076). Ngoài ra, còn cải cách quan chế, khởi xướng việc đắp đê ngăn lũ, và mở rộng luật cấm giết trâu để phát triển nông nghiệp.",
    "Về đối ngoại, thời trị vì chứng kiến một số cuộc chiến tranh giữa Đại Việt với các lân bang. Năm 1075, thấy sắp xâm lược Đại Việt, Nhân Tông sai thái úy đem quân đánh 3 châu của Tống, rồi lui về nước. Quân Tống sang Đại Việt bị đánh bại trong trận Như Nguyệt năm 1077. Năm 1103, lại sai đánh Chiêm Thành, giành thắng lợi. Tuy ở ngôi lâu năm và có nhiều cung phi, Nhân Tông không có con trai để nối dõi. Ông chọn một người cháu gọi ông bằng bác là làm Thái tử kế vị. Sau khi mất, Dương Hoán lên ngôi (tức ), triều đại tiếp tục giai đoạn hưng thịnh."
  ]
}