{
  "name": "Ngô Đình Diệm",
  "birth": [
    "3 tháng 1, 1901",
    "Quảng Bình, Trung Kỳ, Liên bang Đông Dương"
  ],
  "death": [
    "2 tháng 11, 1963 (62 tuổi)",
    "Sài Gòn, Việt Nam Cộng hòa"
  ],
  "infoList": [
    {
      "label": "Nhiệm kỳ",
      "info": [
        "26 tháng 10 năm 1955 – 2 tháng 11 năm 1963",
        "8 năm, 7 ngày"
      ]
    },
    {
      "label": "Tiền nhiệm",
      "info": [
        "Không có"
      ]
    },
    {
      "label": "Kế nhiệm",
      "info": [
        "Nguyễn Văn Thiệu"
      ]
    },
    {
      "label": "Quốc tịch",
      "info": [
        "Việt Nam"
      ]
    }
  ],
  "description": "Ngô Đình Diệm (3 tháng 1 năm 1901 – 2 tháng 11 năm 1963) là nhà chính trị Việt Nam. Ông từng làm quan nhà Nguyễn thời vua Bảo Đại, sau đó làm Thủ tướng cuối cùng của Quốc gia Việt Nam, rồi trở thành Tổng thống đầu tiên của Việt Nam Cộng hòa (Đệ Nhất Cộng hòa Việt Nam) sau khi thành công trong việc phế truất Bảo Đại."
}