{
  "name": "Nguyễn Thì Ung",
  "birth": [],
  "death": [],
  "infoList": [],
  "description": [
    "(1468-?). Người xã Đa Ngưu, huyện Tế Giang. Nay là xã Tân Tiến, , . 26 tuổi đỗ đệ tam giáp đồng tiến sĩ xuất thân khoa Qúy Sửu, niên hiệu Hồng Đức 24 (1493) đời . Cuối đời khi làm Tham Chính (Thanh Hoa). Nguyễn Thì Ung đem thuộc hạ theo tôn phò Giản Tu Công . Sau , lên ngôi (tức ), Nguyễn Thì Ung được phong tước Lương Văn Bá sau thăng Phụng trực đại phu Thượng Thư (1510). Đầu đời Chiêu Tông thăng tước Lương Văn Hầu. Ông có hai con gái một người làm cung phi của vua Thống Nguyên (Cung Hoàng), một người gả cho . Sau khi lên ngôi ông được phong Thiếu Bảo tước Thông Quận Công, sau khi mất được tặng tước Quốc Công."
  ]
}