{
  "name": "Phan Châu Trinh",
  "birth": [
    "Phan Châu Trinh",
    "phủ Tam Kỳ, tỉnh Quảng Nam, Đại Nam"
  ],
  "death": [
    "Sài Gòn, Đông Dương thuộc Pháp"
  ],
  "infoList": [
    {
      "label": "Nơi an nghỉ",
      "info": [
        "Sài Gòn"
      ]
    },
    {
      "label": "Tên khác",
      "info": [
        "Phan Tây Hồ"
      ]
    },
    {
      "label": "Dân tộc",
      "info": [
        "Kinh"
      ]
    },
    {
      "label": "Nghề nghiệp",
      "info": [
        "nhà thơ, nhà văn, nhà hoạt động chính trị"
      ]
    },
    {
      "label": "Người tình",
      "info": [
        "Lê Thị Tỵ (vợ)"
      ]
    },
    {
      "label": "Con cái",
      "info": [
        "Phan Châu Dật (trai)",
        "Phan Thị Châu Liên (gái)",
        "Phan Thị Châu Lan (gái)"
      ]
    },
    {
      "label": "Cha mẹ",
      "info": [
        "Phan Văn Bình (cha)",
        "Lê Thị Chung (mẹ)"
      ]
    }
  ],
  "description": [
    "(còn được gọi ; 1872–1926), hiệu là , , tự là . Ông là nhà thơ, nhà văn, và là nhà hoạt động chính trị thời cận đại trong lịch sử Việt Nam."
  ]
}