{
  "name": "Trần Quang Diệu",
  "birth": [
    "Trần Văn Đạt",
    "09 tháng 09, 1760 (âm lịch)",
    "làng An Hải (trước thuộc huyện Diên Phước, tỉnh Quảng Nam), nay thuộc quận Sơn Trà, thành phố Đà Nẵng"
  ],
  "death": [
    "1802"
  ],
  "infoList": [
    {
      "label": "Nguyên nhân mất",
      "info": [
        "Gia Long xử tử"
      ]
    },
    {
      "label": "Quốc gia",
      "info": [
        "Việt Nam"
      ]
    },
    {
      "label": "Quốc tịch",
      "info": [
        "Việt Nam"
      ]
    },
    {
      "label": "Nghề nghiệp",
      "info": [
        "Thái phó"
      ]
    },
    {
      "label": "Quê quán",
      "info": [
        "làng An Hải, quận Sơn Trà, thành phố Đà Nẵng"
      ]
    },
    {
      "label": "Phối ngẫu",
      "info": [
        "Bùi Thị Xuân"
      ]
    },
    {
      "label": "Con cái",
      "info": [
        "Trần Thị Cúc (Bích Xuân)"
      ]
    },
    {
      "label": "Cha mẹ",
      "info": [
        "Trần Tấn",
        "Phan Thị Hy"
      ]
    }
  ],
  "description": [
    "(chữ Hán: 陳光耀; 1760 – 1802) là một trong của trong lịch sử Việt Nam. Ông cùng với vợ là nữ tướng đã cố sức chiến đấu để bảo vệ vương triều này, nhưng không thành công, và cả hai đều bị vua Gia Long xử tội chết."
  ]
}